kanjidraw/__init__.py
kanjidraw/data.json
kanjidraw/gui.py
kanjidraw/lib.py
kanjidraw-0.2.3.dist-info/LICENSE.AGPLv3
kanjidraw-0.2.3.dist-info/METADATA
kanjidraw-0.2.3.dist-info/WHEEL
kanjidraw-0.2.3.dist-info/entry_points.txt
kanjidraw-0.2.3.dist-info/top_level.txt
kanjidraw-0.2.3.dist-info/RECORD
