Metadata-Version: 2.1
Name: kanjidraw
Version: 0.2.3
Summary: handwritten kanji recognition
Home-page: https://github.com/obfusk/kanjidraw
Author: Felix C. Stegerman
Author-email: flx@obfusk.net
License: AGPLv3+
Keywords: japanese kanji draw handwriting
Platform: UNKNOWN
Classifier: Development Status :: 4 - Beta
Classifier: Intended Audience :: Developers
Classifier: Intended Audience :: End Users/Desktop
Classifier: License :: OSI Approved :: GNU Affero General Public License v3 or later (AGPLv3+)
Classifier: Natural Language :: Japanese
Classifier: Operating System :: POSIX :: Linux
Classifier: Programming Language :: Python :: 3
Classifier: Programming Language :: Python :: 3.5
Classifier: Programming Language :: Python :: 3.6
Classifier: Programming Language :: Python :: 3.7
Classifier: Programming Language :: Python :: 3.8
Classifier: Programming Language :: Python :: 3.9
Classifier: Programming Language :: Python :: Implementation :: CPython
Classifier: Topic :: Text Processing
Classifier: Topic :: Utilities
Requires-Python: >=3.5
